mkdocs_chessboard_plugin/__init__.py
mkdocs_chessboard_plugin/plugin.py
mkdocs_chessboard_plugin-0.1.7.dist-info/METADATA
mkdocs_chessboard_plugin-0.1.7.dist-info/WHEEL
mkdocs_chessboard_plugin-0.1.7.dist-info/entry_points.txt
mkdocs_chessboard_plugin-0.1.7.dist-info/RECORD
